elementary_flask/__init__.py
elementary_flask/_consts.py
elementary_flask/app.py
elementary_flask/form.py
elementary_flask/globals.py
elementary_flask/listing.py
elementary_flask/templating.py
elementary_flask/themes.py
elementary_flask/typing.py
elementary_flask/blueprint/__init__.py
elementary_flask/blueprint/blueprint.py
elementary_flask/blueprint/scaffold.py
elementary_flask/components/__init__.py
elementary_flask/components/_component/__init__.py
elementary_flask/components/_component/component.py
elementary_flask/components/_component/container.py
elementary_flask/components/_component/element_component.py
elementary_flask/components/_component/weak_component.py
elementary_flask/components/bootstrap/__init__.py
elementary_flask/components/bootstrap/components.py
elementary_flask/components/bootstrap/containers.py
elementary_flask/components/general/__init__.py
elementary_flask/components/general/favicon.py
elementary_flask/components/general/icon.py
elementary_flask/components/page/__init__.py
elementary_flask/components/page/page.py
elementary_flask/components/page/page_layout.py
elementary_flask/components/page/page_response.py
elementary_flask/components/page/theme.py
elementary_flask/components/page/view_function.py
elementary_flask/components/weak/__init__.py
elementary_flask/components/weak/http_error.py
elementary_flask/components/weak/form/__init__.py
elementary_flask/components/weak/form/decorators.py
elementary_flask/components/weak/form/dom_manipulation.py
elementary_flask/components/weak/form/endpoint.py
elementary_flask/components/weak/form/render.py
elementary_flask/components/weak/form/response.py
elementary_flask/components/weak/form/state.py
elementary_flask/components/weak/listing/__init__.py
elementary_flask/components/weak/listing/_page_uri.py
elementary_flask/components/weak/listing/action.py
elementary_flask/components/weak/listing/column.py
elementary_flask/components/weak/listing/filter.py
elementary_flask-0.0.1.dev17.dist-info/LICENSE
elementary_flask-0.0.1.dev17.dist-info/METADATA
elementary_flask-0.0.1.dev17.dist-info/WHEEL
elementary_flask-0.0.1.dev17.dist-info/top_level.txt
elementary_flask-0.0.1.dev17.dist-info/RECORD
