Metadata-Version: 2.1
Name: elementary-flask
Version: 0.0.1.dev17
Summary: Component based framework for Flask/Python
Home-page: https://github.com/xaled/elementary_flask
Author: Khalid Grandi
Author-email: kh.grandi@gmail.com
License: MIT
Project-URL: Bug Tracker, https://github.com/xaled/elementary_flask/issues
Platform: any
Classifier: Programming Language :: Python :: 3
Classifier: License :: OSI Approved :: MIT License
Classifier: Operating System :: OS Independent
Requires-Python: >=3.6
License-File: LICENSE
Requires-Dist: Flask (==2.2.2)
Requires-Dist: Flask-WTF (~=1.0.0)
Requires-Dist: Jinja2 (==3.1.2)
Requires-Dist: MarkupSafe (~=2.1.1)
Requires-Dist: croniter (==1.3.5)
Requires-Dist: redis (==4.3.4)
Requires-Dist: pottery
Requires-Dist: PyYAML (~=6.0)
Requires-Dist: WTForms (~=3.0.1)
Requires-Dist: Werkzeug (==2.2.2)
Requires-Dist: setuptools (==65.2.0)
Requires-Dist: Flask-Caching
